Encoder_83/design.sv
module encoder83 (
    input  logic [7:0] In,
    output logic [2:0] Out
);

    always_comb begin
        case (In)
            8'b00000001: Out = 3'b000;
            8'b00000010: Out = 3'b001;
            8'b00000100: Out = 3'b010;
            8'b00001000: Out = 3'b011;
            8'b00010000: Out = 3'b100;
            8'b00100000: Out = 3'b101;
            8'b01000000: Out = 3'b110;
            8'b10000000: Out = 3'b111;
            default:     Out = 3'b000;
        endcase
    end

endmodule

Encoder_83/testbench.sv
module tb_encoder83;

    logic [7:0] In;
    logic [2:0] Out;

    encoder83 uut (
        .In(In),
        .Out(Out)
    );

    initial begin
        $dumpfile("dump.vcd");
      $dumpvars(0, tb_encoder83);
        In = 8'b00000001;
        #10;
        $display("In = %b : Out = %b", In, Out);

        In = 8'b00000010;
        #10;
        $display("In = %b : Out = %b", In, Out);

        In = 8'b00000100;
        #10;
        $display("In = %b : Out = %b", In, Out);

        In = 8'b00001000;
        #10;
        $display("In = %b : Out = %b", In, Out);

        In = 8'b00010000;
        #10;
        $display("In = %b : Out = %b", In, Out);

        In = 8'b00100000;
        #10;
        $display("In = %b : Out = %b", In, Out);

        In = 8'b01000000;
        #10;
        $display("In = %b : Out = %b", In, Out);

        In = 8'b10000000;
        #10;
        $display("In = %b : Out = %b", In, Out);

        $finish;
    end

endmodule

Encoder_83/dump.vcd
$date
	Sun Oct 20 03:15:52 2024
$end
$version
	QuestaSim Version 2023.1
$end
$timescale
	1ns
$end

$scope module tb_encoder83 $end
$var reg 8 ! In [7:0] $end
$var reg 3 " Out [2:0] $end

$scope module uut $end
$var wire 1 # In [7] $end
$var wire 1 $ In [6] $end
$var wire 1 % In [5] $end
$var wire 1 & In [4] $end
$var wire 1 ' In [3] $end
$var wire 1 ( In [2] $end
$var wire 1 ) In [1] $end
$var wire 1 * In [0] $end
$var reg 3 + Out [2:0] $end
$upscope $end
$upscope $end
$enddefinitions $end
#0
$dumpvars
1*
0)
0(
0'
0&
0%
0$
0#
b1 !
b0 "
b0 +
$end
#10
b10 !
0*
1)
b1 +
b1 "
#20
b100 !
0)
1(
b10 +
b10 "
#30
b1000 !
0(
1'
b11 +
b11 "
#40
b10000 !
0'
1&
b100 +
b100 "
#50
b100000 !
0&
1%
b101 +
b101 "
#60
b1000000 !
0%
1$
b110 +
b110 "
#70
b10000000 !
0$
1#
b111 +
b111 "
