Full_subtractor/design.sv
module full_subtractor(
    input logic A,
    input logic B,
    input logic Bin,
    output logic D,
    output logic Bout
);

    assign D = A ^ B ^ Bin;
    assign Bout = (~A & (B | Bin)) | (B & Bin);

endmodule

Full_subtractor/testbench.sv
module tb_full_subtractor;

    logic A, B, Bin;
    logic D, Bout;

    full_subtractor uut (
        .A(A),
        .B(B),
        .Bin(Bin),
        .D(D),
        .Bout(Bout)
    );

    initial begin
        
        $dumpfile("dump.vcd");
      $dumpvars(0, tb_full_subtractor);
        $monitor("A=%b B=%b Bin=%b | D=%b Bout=%b", A, B, Bin, D, Bout);

        
        A = 0; B = 0; Bin = 0;
        #10;
        
        A = 0; B = 0; Bin = 1;
        #10;
        
        A = 0; B = 1; Bin = 0;
        #10;
        
        A = 0; B = 1; Bin = 1;
        #10;
        
        A = 1; B = 0; Bin = 0;
        #10;
        
        A = 1; B = 0; Bin = 1;
        #10;
       
        A = 1; B = 1; Bin = 0;
        #10;
       
        A = 1; B = 1; Bin = 1;
        #10;

        $finish;
    end

endmodule

Full_subtractor/dump.vcd
$date
	Sun Oct 20 02:56:02 2024
$end
$version
	QuestaSim Version 2023.1
$end
$timescale
	1ns
$end

$scope module tb_full_subtractor $end
$var reg 1 ! A $end
$var reg 1 " B $end
$var reg 1 # Bin $end
$var reg 1 $ Bout $end
$var reg 1 % D $end

$scope module uut $end
$var wire 1 & A $end
$var wire 1 ' B $end
$var wire 1 ( Bin $end
$var reg 1 ) Bout $end
$var reg 1 * D $end
$upscope $end
$upscope $end
$enddefinitions $end
#0
$dumpvars
0(
0'
0&
0!
0"
0#
0$
0%
0)
0*
$end
#10
1#
1(
1*
1)
1$
1%
#20
1"
0#
1'
0(
#30
1#
1(
0*
0%
#40
1!
0"
0#
1&
0'
0(
1*
0)
0$
1%
#50
1#
1(
0*
0%
#60
1"
0#
1'
0(
#70
1#
1(
1*
1)
1$
1%
