DFF_async_res/design.sv
module d_flip_flop_async_reset (
    input  logic D,
    input  logic clk,
    input  logic reset_n,
    output logic Q
);

    always_ff @(posedge clk or negedge reset_n) begin
        if (!reset_n)
            Q <= 0;
        else
            Q <= D;
    end

endmodule

DFF_async_res/testbench.sv
module tb_d_flip_flop_async_reset;

    logic D;
    logic clk;
    logic reset_n;
    logic Q;

    d_flip_flop_async_reset uut (
        .D(D),
        .clk(clk),
        .reset_n(reset_n),
        .Q(Q)
    );

    initial begin
        clk = 0;
        forever #5 clk = ~clk;
    end

    initial begin
      $dumpfile("dump.vcd");
      $dumpvars(0, tb_d_flip_flop_async_reset);
        reset_n = 0;
        D = 0;
        #10;
        
        reset_n = 1;
        D = 1;
        #10;
        $display("D = %b, reset_n = %b, Q = %b", D, reset_n, Q);
        
        D = 0;
        #10;
        $display("D = %b, reset_n = %b, Q = %b", D, reset_n, Q);

        reset_n = 0;
        #10;
        $display("D = %b, reset_n = %b, Q = %b", D, reset_n, Q);

        reset_n = 1;
        D = 1;
        #10;
        $display("D = %b, reset_n = %b, Q = %b", D, reset_n, Q);

        $finish;
    end

endmodule

DFF_async_res/dump.vcd
$date
	Sun Oct 20 03:36:29 2024
$end
$version
	QuestaSim Version 2023.1
$end
$timescale
	1ns
$end

$scope module tb_d_flip_flop_async_reset $end
$var reg 1 ! D $end
$var reg 1 " Q $end
$var reg 1 # clk $end
$var reg 1 $ reset_n $end

$scope module uut $end
$var wire 1 % D $end
$var wire 1 & clk $end
$var wire 1 ' reset_n $end
$var reg 1 ( Q $end
$upscope $end
$upscope $end
$enddefinitions $end
#0
$dumpvars
0'
0&
0%
0!
0"
0#
0$
0(
$end
#5
1#
1&
#10
1$
1!
0#
1%
1'
0&
#15
1#
1&
1(
1"
#20
0!
0#
0%
0&
#25
1#
1&
0(
0"
#30
0$
0#
0'
0&
#35
1#
1&
#40
1$
1!
0#
1%
1'
0&
#45
1#
1&
1(
1"
