Decoder_parameterized/design.sv
module decoderNto2N #(parameter N = 3) (
    input  logic [N-1:0] In,
    output logic [2**N-1:0] Out
);

    always_comb begin
        Out = '0;
        Out[In] = 1'b1;
    end

endmodule

Decoder_parameterized/testbench.sv
module tb_decoderNto2N;

    parameter N = 3;
    parameter OUT_WIDTH = 2**N;

    logic [N-1:0] In;
    logic [OUT_WIDTH-1:0] Out;

    decoderNto2N #(N) uut (
        .In(In),
        .Out(Out)
    );

    initial begin
        $dumpfile("dump.vcd");
      $dumpvars(0, tb_decoderNto2N);
        In = 3'b000;
        #10;
        $display("In = %b : Out = %b", In, Out);

        In = 3'b001;
        #10;
        $display("In = %b : Out = %b", In, Out);

        In = 3'b010;
        #10;
        $display("In = %b : Out = %b", In, Out);

        In = 3'b011;
        #10;
        $display("In = %b : Out = %b", In, Out);

        In = 3'b100;
        #10;
        $display("In = %b : Out = %b", In, Out);

        In = 3'b101;
        #10;
        $display("In = %b : Out = %b", In, Out);

        In = 3'b110;
        #10;
        $display("In = %b : Out = %b", In, Out);

        In = 3'b111;
        #10;
        $display("In = %b : Out = %b", In, Out);

        $finish;
    end

endmodule

Decoder_parameterized/dump.vcd
$date
	Sun Oct 20 03:32:55 2024
$end
$version
	QuestaSim Version 2023.1
$end
$timescale
	1ns
$end

$scope module tb_decoderNto2N $end
$var parameter 32 ! N $end
$var parameter 32 " OUT_WIDTH $end
$var reg 3 # In [2:0] $end
$var reg 8 $ Out [7:0] $end

$scope module uut $end
$var wire 1 % In [2] $end
$var wire 1 & In [1] $end
$var wire 1 ' In [0] $end
$var parameter 32 ( N $end
$var reg 8 ) Out [7:0] $end
$upscope $end
$upscope $end
$enddefinitions $end
#0
$dumpvars
0'
0&
0%
b11 !
b1000 "
b0 #
b1 $
b11 (
b1 )
$end
#10
b1 #
1'
b10 )
b10 $
#20
b10 #
0'
1&
b100 )
b100 $
#30
b11 #
1'
b1000 )
b1000 $
#40
b100 #
0'
0&
1%
b10000 )
b10000 $
#50
b101 #
1'
b100000 )
b100000 $
#60
b110 #
0'
1&
b1000000 )
b1000000 $
#70
b111 #
1'
b10000000 )
b10000000 $
