Decoder_38/design.sv
module decoder38 (
    input  logic [2:0] In,
    output logic [7:0] Out
);

    always_comb begin
        Out = 8'b00000000;
        case (In)
            3'b000: Out[0] = 1'b1;
            3'b001: Out[1] = 1'b1;
            3'b010: Out[2] = 1'b1;
            3'b011: Out[3] = 1'b1;
            3'b100: Out[4] = 1'b1;
            3'b101: Out[5] = 1'b1;
            3'b110: Out[6] = 1'b1;
            3'b111: Out[7] = 1'b1;
        endcase
    end

endmodule

Decoder_38/testbench.sv
module tb_decoder38;

    logic [2:0] In;
    logic [7:0] Out;

    decoder38 uut (
        .In(In),
        .Out(Out)
    );

    initial begin
        $dumpfile("dump.vcd");
      $dumpvars(0, tb_decoder38);
        In = 3'b000;
        #10;
        $display("In = %b : Out = %b", In, Out);

        In = 3'b001;
        #10;
        $display("In = %b : Out = %b", In, Out);

        In = 3'b010;
        #10;
        $display("In = %b : Out = %b", In, Out);

        In = 3'b011;
        #10;
        $display("In = %b : Out = %b", In, Out);

        In = 3'b100;
        #10;
        $display("In = %b : Out = %b", In, Out);

        In = 3'b101;
        #10;
        $display("In = %b : Out = %b", In, Out);

        In = 3'b110;
        #10;
        $display("In = %b : Out = %b", In, Out);

        In = 3'b111;
        #10;
        $display("In = %b : Out = %b", In, Out);

        $finish;
    end

endmodule

Decoder_38/dump.vcd
$date
	Sun Oct 20 03:31:52 2024
$end
$version
	QuestaSim Version 2023.1
$end
$timescale
	1ns
$end

$scope module tb_decoder38 $end
$var reg 3 ! In [2:0] $end
$var reg 8 " Out [7:0] $end

$scope module uut $end
$var wire 1 # In [2] $end
$var wire 1 $ In [1] $end
$var wire 1 % In [0] $end
$var reg 8 & Out [7:0] $end
$upscope $end
$upscope $end
$enddefinitions $end
#0
$dumpvars
0%
0$
0#
b0 !
b1 "
b1 &
$end
#10
b1 !
1%
b10 &
b10 "
#20
b10 !
0%
1$
b100 &
b100 "
#30
b11 !
1%
b1000 &
b1000 "
#40
b100 !
0%
0$
1#
b10000 &
b10000 "
#50
b101 !
1%
b100000 &
b100000 "
#60
b110 !
0%
1$
b1000000 &
b1000000 "
#70
b111 !
1%
b10000000 &
b10000000 "
