DFF_sync_res/design.sv
module d_flip_flop_sync_reset (
    input  logic D,
    input  logic clk,
    input  logic reset,
    output logic Q
);

    always_ff @(posedge clk) begin
        if (reset)
            Q <= 0;
        else
            Q <= D;
    end

endmodule

DFF_sync_res/testbench.sv
module tb_d_flip_flop_sync_reset;

    logic D;
    logic clk;
    logic reset;
    logic Q;

    d_flip_flop_sync_reset uut (
        .D(D),
        .clk(clk),
        .reset(reset),
        .Q(Q)
    );

    initial begin
        clk = 0;
        forever #5 clk = ~clk;
    end

    initial begin
        $dumpfile("dump.vcd");
      $dumpvars(0, tb_d_flip_flop_sync_reset);
        
        reset = 1;
        D = 0;
        #10;
        
        reset = 0;
        D = 1;
        #10;
        $display("D = %b, reset = %b, Q = %b", D, reset, Q);
        
        D = 0;
        #10;
        $display("D = %b, reset = %b, Q = %b", D, reset, Q);

        reset = 1;
        #10;
        $display("D = %b, reset = %b, Q = %b", D, reset, Q);

        reset = 0;
        D = 1;
        #10;
        $display("D = %b, reset = %b, Q = %b", D, reset, Q);

        $finish;
    end

endmodule

DFF_sync_res/dump.vcd
$date
	Sun Oct 20 03:36:56 2024
$end
$version
	QuestaSim Version 2023.1
$end
$timescale
	1ns
$end

$scope module tb_d_flip_flop_sync_reset $end
$var reg 1 ! D $end
$var reg 1 " Q $end
$var reg 1 # clk $end
$var reg 1 $ reset $end

$scope module uut $end
$var wire 1 % D $end
$var wire 1 & clk $end
$var wire 1 ' reset $end
$var reg 1 ( Q $end
$upscope $end
$upscope $end
$enddefinitions $end
#0
$dumpvars
1'
0&
0%
0!
x"
0#
1$
x(
$end
#5
1#
1&
0(
0"
#10
0$
1!
0#
0'
1%
0&
#15
1#
1&
1(
1"
#20
0!
0#
0%
0&
#25
1#
1&
0(
0"
#30
1$
0#
1'
0&
#35
1#
1&
#40
0$
1!
0#
0'
1%
0&
#45
1#
1&
1(
1"
