Full_adder/design.sv
module full_adder (
    input logic a,
    input logic b,
    input logic cin,
    output logic sum,
    output logic carry
);

    assign sum = a ^ b ^ cin;
    assign carry = (a & b) | (b & cin) | (a & cin);

endmodule

Full_adder/testbench.sv
module full_adder_tb;

    logic tb_a;
    logic tb_b;
    logic tb_cin;
    logic tb_sum;
    logic tb_carry;

    full_adder uut (
        .a(tb_a),
        .b(tb_b),
        .cin(tb_cin),
        .sum(tb_sum),
        .carry(tb_carry)
    );

    initial begin
        $dumpfile("dump.vcd");
      $dumpvars(0, full_adder_tb);
        $display("A B Cin | Sum Carry");
        $display("--------|----------");

        tb_a = 0; tb_b = 0; tb_cin = 0;
        #10;
        $display("%0d %0d  %0d  |  %0d   %0d", tb_a, tb_b, tb_cin, tb_sum, tb_carry);

        tb_a = 0; tb_b = 0; tb_cin = 1;
        #10;
        $display("%0d %0d  %0d  |  %0d   %0d", tb_a, tb_b, tb_cin, tb_sum, tb_carry);

        tb_a = 0; tb_b = 1; tb_cin = 0;
        #10;
        $display("%0d %0d  %0d  |  %0d   %0d", tb_a, tb_b, tb_cin, tb_sum, tb_carry);

        tb_a = 0; tb_b = 1; tb_cin = 1;
        #10;
        $display("%0d %0d  %0d  |  %0d   %0d", tb_a, tb_b, tb_cin, tb_sum, tb_carry);

        tb_a = 1; tb_b = 0; tb_cin = 0;
        #10;
        $display("%0d %0d  %0d  |  %0d   %0d", tb_a, tb_b, tb_cin, tb_sum, tb_carry);

        tb_a = 1; tb_b = 0; tb_cin = 1;
        #10;
        $display("%0d %0d  %0d  |  %0d   %0d", tb_a, tb_b, tb_cin, tb_sum, tb_carry);

        tb_a = 1; tb_b = 1; tb_cin = 0;
        #10;
        $display("%0d %0d  %0d  |  %0d   %0d", tb_a, tb_b, tb_cin, tb_sum, tb_carry);

        tb_a = 1; tb_b = 1; tb_cin = 1;
        #10;
        $display("%0d %0d  %0d  |  %0d   %0d", tb_a, tb_b, tb_cin, tb_sum, tb_carry);

        $finish;
    end

endmodule

Full_adder/dump.vcd
$date
	Sun Oct 20 02:53:23 2024
$end
$version
	QuestaSim Version 2023.1
$end
$timescale
	1ns
$end

$scope module full_adder_tb $end
$var reg 1 ! tb_a $end
$var reg 1 " tb_b $end
$var reg 1 # tb_carry $end
$var reg 1 $ tb_cin $end
$var reg 1 % tb_sum $end

$scope module uut $end
$var wire 1 & a $end
$var wire 1 ' b $end
$var wire 1 ( cin $end
$var reg 1 ) carry $end
$var reg 1 * sum $end
$upscope $end
$upscope $end
$enddefinitions $end
#0
$dumpvars
0(
0'
0&
0!
0"
0#
0$
0%
0)
0*
$end
#10
1$
1(
1*
1%
#20
1"
0$
1'
0(
#30
1$
1(
0*
1)
1#
0%
#40
1!
0"
0$
1&
0'
0(
1*
0)
0#
1%
#50
1$
1(
0*
1)
1#
0%
#60
1"
0$
1'
0(
#70
1$
1(
1*
1%
